mitreattack/__init__.py
mitreattack/attackToExcel/README.md
mitreattack/attackToExcel/__init__.py
mitreattack/attackToExcel/attackToExcel.py
mitreattack/attackToExcel/stixToDf.py
mitreattack/collections/README.md
mitreattack/collections/__init__.py
mitreattack/collections/collection_to_index.py
mitreattack/collections/index_to_markdown.py
mitreattack/constants.py
mitreattack/diffStix/README.md
mitreattack/diffStix/__init__.py
mitreattack/diffStix/changelog_helper.py
mitreattack/download_stix.py
mitreattack/navlayers/README.md
mitreattack/navlayers/__init__.py
mitreattack/navlayers/core/README.md
mitreattack/navlayers/core/__init__.py
mitreattack/navlayers/core/exceptions.py
mitreattack/navlayers/core/filter.py
mitreattack/navlayers/core/gradient.py
mitreattack/navlayers/core/helpers.py
mitreattack/navlayers/core/layer.py
mitreattack/navlayers/core/layerobj.py
mitreattack/navlayers/core/layout.py
mitreattack/navlayers/core/legenditem.py
mitreattack/navlayers/core/metadata.py
mitreattack/navlayers/core/objlink.py
mitreattack/navlayers/core/technique.py
mitreattack/navlayers/core/versions.py
mitreattack/navlayers/exporters/__init__.py
mitreattack/navlayers/exporters/excel_templates.py
mitreattack/navlayers/exporters/fonts/monospace.ttf
mitreattack/navlayers/exporters/fonts/sans-serif.ttf
mitreattack/navlayers/exporters/fonts/serif.ttf
mitreattack/navlayers/exporters/matrix_gen.py
mitreattack/navlayers/exporters/svg_objects.py
mitreattack/navlayers/exporters/svg_templates.py
mitreattack/navlayers/exporters/to_excel.py
mitreattack/navlayers/exporters/to_svg.py
mitreattack/navlayers/generators/__init__.py
mitreattack/navlayers/generators/gen_helpers.py
mitreattack/navlayers/generators/overview_generator.py
mitreattack/navlayers/generators/sum_generator.py
mitreattack/navlayers/generators/usage_generator.py
mitreattack/navlayers/layerExporter_cli.py
mitreattack/navlayers/layerGenerator_cli.py
mitreattack/navlayers/manipulators/__init__.py
mitreattack_python-5.3.0.dist-info/METADATA
mitreattack_python-5.3.0.dist-info/WHEEL
mitreattack_python-5.3.0.dist-info/entry_points.txt
mitreattack_python-5.3.0.dist-info/licenses/LICENSE.txt
mitreattack_python-5.3.0.dist-info/licenses/NOTICE.txt
mitreattack_python-5.3.0.dist-info/RECORD
