Metadata-Version: 2.4
Name: mitreattack-python
Version: 5.3.0
Summary: MITRE ATT&CK python library
License: Apache-2.0
License-File: LICENSE.txt
License-File: NOTICE.txt
Author: MITRE ATT&CK
Author-email: attack@mitre.org
Requires-Python: >=3.11,<4.0
Classifier: License :: OSI Approved :: Apache Software License
Classifier: Operating System :: OS Independent
Classifier: Programming Language :: Python :: 3
Classifier: Programming Language :: Python :: 3.11
Classifier: Programming Language :: Python :: 3.12
Classifier: Programming Language :: Python :: 3.13
Classifier: Programming Language :: Python :: 3.14
Classifier: Topic :: Security
Requires-Dist: Markdown (>=3.5)
Requires-Dist: Pillow (>=10.1.0)
Requires-Dist: colour (>=0.1.5)
Requires-Dist: deepdiff (>=6.6.0)
Requires-Dist: drawsvg (>=2.4.0)
Requires-Dist: loguru (>=0.6.0)
Requires-Dist: numpy (>=1.26.1)
Requires-Dist: openpyxl (>=3.1.2)
Requires-Dist: pandas (>=2.1.1)
Requires-Dist: pooch (>=1.7.0)
Requires-Dist: python-dateutil (>=2.8.2)
Requires-Dist: requests (>=2.31.0)
Requires-Dist: rich (>=13.6.0)
Requires-Dist: stix2 (>=3.0.1)
Requires-Dist: tabulate (>=0.9.0)
Requires-Dist: tqdm (>=4.66.1)
Requires-Dist: typer (>=0.9.0)
Requires-Dist: wheel (>=0.41.2)
Requires-Dist: xlsxwriter (>=3.1.8)
Project-URL: Documentation, https://mitreattack-python.readthedocs.io/
Project-URL: Homepage, https://github.com/mitre-attack/mitreattack-python/
Project-URL: Repository, https://github.com/mitre-attack/mitreattack-python/
